Metadata-Version: 2.1
Name: gributils-annotator
Version: 0.7
Summary: Weather annotation service for streams of newline sepratade json positional messages based on gributils
Home-page: https://github.com/innovationgarage/gributils-annotator
Author: Egil Moeller
Author-email: egil@innovationgarage.no
License: UNKNOWN
Platform: UNKNOWN
